<?xml version="1.0" encoding="UTF-8"?><!DOCTYPE historysamples PUBLIC "SYSTEM" "chronos-history.dtd"><history timestamp="1444232470477" gcRatio="0.0" collectedPrSecond="0.0" responsetimeAverage="2804.569444444444" responsetime95Percentile="5885.249999999999" maxAverageThroughput="2.270576746210372"><individualPercentiles><entry key="4.2 SearchGET_MetaData" value="3659.0"/><entry key="1.Publish" value="4343.0"/><entry key="2.Delete" value="4302.0"/><entry key="4.3 SearchGET_Index" value="2123.0"/><entry key="3.Retrieve" value="5442.0"/><entry key="4.1 SearchGET_Master" value="75216.0"/></individualPercentiles><individualAverages><entry key="4.2 SearchGET_MetaData" value="1381.0"/><entry key="1.Publish" value="1545.0"/><entry key="2.Delete" value="1521.6666666666665"/><entry key="4.3 SearchGET_Index" value="1143.3333333333333"/><entry key="3.Retrieve" value="1921.3333333333333"/><entry key="4.1 SearchGET_Master" value="9315.083333333334"/></individualAverages></history>